laue_dials/__init__.py
laue_dials/algorithms/diffgeo.py
laue_dials/algorithms/integration.py
laue_dials/algorithms/laue.py
laue_dials/algorithms/monochromatic.py
laue_dials/algorithms/outliers.py
laue_dials/command_line/compute_rmsds.py
laue_dials/command_line/find_spots.py
laue_dials/command_line/index.py
laue_dials/command_line/integrate.py
laue_dials/command_line/optimize_indexing.py
laue_dials/command_line/plot_wavelengths.py
laue_dials/command_line/predict.py
laue_dials/command_line/refine.py
laue_dials/command_line/sequence_to_stills.py
laue_dials/command_line/version.py
laue_dials/diagnostics/compare_A_matrices.py
laue_dials/diagnostics/diffgeolib.py
laue_dials/diagnostics/match_precog_hkls.py
laue_dials/diagnostics/quintile_strongs.py
laue_dials/diagnostics/viewer.py
laue_dials/utils/matching.py
laue_dials/utils/version.py
laue_dials-0.5.dist-info/LICENSE.txt
laue_dials-0.5.dist-info/METADATA
laue_dials-0.5.dist-info/WHEEL
laue_dials-0.5.dist-info/entry_points.txt
laue_dials-0.5.dist-info/top_level.txt
laue_dials-0.5.dist-info/RECORD
