Metadata-Version: 2.2
Name: laue_dials
Version: 0.5
Summary: A package for analyzing Laue x-ray crystallography data using the DIALS framework.
Home-page: https://github.com/rs-station/laue_dials
Author: Rick A. Hewitt
Author-email: rahewitt@g.harvard.edu
License: MIT
Platform: Mac
Platform: Linux
Classifier: Development Status :: 4 - Beta
Classifier: Programming Language :: Python
Requires-Python: >=3.8
License-File: LICENSE.txt
Requires-Dist: importlib-metadata
Requires-Dist: reciprocalspaceship
Requires-Dist: tqdm
Requires-Dist: numpy
Requires-Dist: pandas
Requires-Dist: argparse
Requires-Dist: gemmi
Requires-Dist: matplotlib
Requires-Dist: scipy
Requires-Dist: jupyter
Provides-Extra: docs
Requires-Dist: sphinx; extra == "docs"
Requires-Dist: myst_parser; extra == "docs"
Requires-Dist: sphinxcontrib_autoprogram; extra == "docs"
Requires-Dist: sphinx_rtd_theme; extra == "docs"
Requires-Dist: nbsphinx; extra == "docs"
Requires-Dist: sphinx-design; extra == "docs"
Requires-Dist: autodocsumm; extra == "docs"
Requires-Dist: pandoc; extra == "docs"
Provides-Extra: testing
Requires-Dist: setuptools>=61; extra == "testing"
Requires-Dist: pytest; extra == "testing"
Requires-Dist: pytest-cov; extra == "testing"
